Workbook

Sheet Sheet1
A1: OrderID | B1: Date | C1: CustomerID | D1: Product | E1: Quantity | F1: UnitPrice | G1: ShippingAddress | H1: PaymentMethod | I1: OrderStatus | J1: TrackingNumber | K1: ItemsInCart | L1: CouponCode | M1: ReferralSource | N1: TotalPrice
A2: ORD200000 | B2: 44930 | C2: C72649 | D2: Monitor | E2: 5 | F2: 570.62 | G2: 928 Main St | H2: Debit Card | I2: Shipped | J2: TRK37947903 | K2: 7 | L2: SAVE10 | M2: Instagram | N2: 2853.1
A3: ORD200001 | B3: 45527 | C3: C75739 | D3: Phone | E3: 2 | F3: 151.35 | G3: 823 Main St | H3: Online | I3: Shipped | J3: TRK91186779 | K3: 3 | L3: SAVE10 | M3: Referral | N3: 302.7
A4: ORD200002 | B4: 45349 | C4: C81728 | D4: Tablet | E4: 5 | F4: 550.68 | G4: 512 Main St | H4: Credit Card | I4: Cancelled | J4: TRK42903982 | K4: 8 | L4: FREESHIP | M4: Email | N4: 2753.4
A5: ORD200003 | B5: 45214 | C5: C33540 | D5: Chair | E5: 1 | F5: 273.19 | G5: 275 Main St | H5: Debit Card | I5: Returned | J5: TRK62788070 | K5: 5 | L5: SAVE10 | M5: Facebook | N5: 273.19
A6: ORD200004 | B6: 45785 | C6: C81840 | D6: Printer | E6: 4 | F6: 626.01 | G6: 668 Main St | H6: Online | I6: Delivered | J6: TRK29241424 | K6: 8 | L6: SAVE10 | M6: Email | N6: 2504.04
A7: ORD200005 | B7: 45222 | C7: C37249 | D7: Phone | E7: 2 | F7: 245.86 | G7: 934 Main St | H7: Credit Card | I7: Shipped | J7: TRK72976927 | K7: 4 | L7: SAVE10 | M7: Instagram | N7: 491.72
A8: ORD200006 | B8: 45825 | C8: C83492 | D8: Laptop | E8: 1 | F8: 664.42 | G8: 986 Main St | H8: Gift Card | I8: Returned | J8: TRK96417362 | K8: 6 | L8: SAVE10 | M8: Facebook | N8: 664.42
A9: ORD200007 | B9: 45058 | C9: C41460 | D9: Monitor | E9: 5 | F9: 149.55 | G9: 706 Main St | H9: Cash | I9: Shipped | J9: TRK78809193 | K9: 9 | L9: FREESHIP | M9: Facebook | N9: 747.75
A10: ORD200008 | B10: 45749 | C10: C26817 | D10: Phone | E10: 2 | F10: 134.28 | G10: 904 Main St | H10: Gift Card | I10: Cancelled | J10: TRK61042692 | K10: 2 | L10: No coupon | M10: Email | N10: 268.56
A11: ORD200009 | B11: 45251 | C11: C31946 | D11: Desk | E11: 4 | F11: 509.38 | G11: 102 Main St | H11: Credit Card | I11: Shipped | J11: TRK33478363 | K11: 6 | L11: SAVE10 | M11: Google | N11: 2037.52
A12: ORD200010 | B12: 45289 | C12: C43443 | D12: Tablet | E12: 5 | F12: 625.97 | G12: 333 Main St | H12: Credit Card | I12: Returned | J12: TRK98859248 | K12: 9 | L12: WINTER15 | M12: Instagram | N12: 3129.85
A13: ORD200011 | B13: 45339 | C13: C93861 | D13: Monitor | E13: 3 | F13: 49.14 | G13: 831 Main St | H13: Online | I13: Returned | J13: TRK48234646 | K13: 7 | L13: SAVE10 | M13: Email | N13: 147.42
... A1201: ORD201199 | B1201: 45088 | C1201: C57502 | D1201: Tablet | E1201: 4 | F1201: 560.58 | G1201: 201 Main St | H1201: Gift Card | I1201: Returned | J1201: TRK51116746 | K1201: 6 | L1201: SAVE10 | M1201: Referral | N1201: 2242.32

Sheet Sheet2
A2: Statistics table | F2: IQR Outlier Table | I2: Revenue by Product | L2: Orders by Status | O2: Revenue by Payment Method
A3: Metric | B3: Total Price | C3: Unit Price | D3: Quantity | F3: Q1 | G3: =QUARTILE(Sheet1!N2:N1201,1) -> 410.52 | I3: Product | J3: Total Revenue | L3: Order Status | M3: Order Count | O3: Payment Method | P3: Total Revenue
A4: Count | B4: =COUNT(Sheet1!N2:N1201) -> 1200 | C4: =COUNT(Sheet1!F2:F1201) -> 1200 | D4: =COUNT(Sheet1!E2:E1201) -> 1200 | F4: Q3 | G4: =QUARTILE(Sheet1!N2:N1201,3) -> 1578.475 | I4: Chair | J4: =SUMIF(Sheet1!D2:D1201,"Chair",Sheet1!N2:N1201) -> 195620.11 | L4: Cancelled | M4: =COUNTIF(Sheet1!I2:I1201,"Cancelled") -> 250 | O4: Credit Card | P4: =SUMIF(Sheet1!H2:H1201,"Credit Card",Sheet1!N2:N1201) -> 263847.63
A5: Mean | B5: =AVERAGE(Sheet1!N2:N1201) -> 1053.9683 | C5: =AVERAGE(Sheet1!F2:F1201) -> 356.41275 | D5: =AVERAGE(Sheet1!E2:E1201) -> 2.9458333 | F5: IQR | G5: =G4-G3 -> 1167.955 | I5: Printer | J5: =SUMIF(Sheet1!D2:D1201,"Printer",Sheet1!N2:N1201) -> 195612.61 | L5: Returned | M5: =COUNTIF(Sheet1!I2:I1201,"Returned") -> 247 | O5: Online | P5: =SUMIF(Sheet1!H2:H1201,"Online",Sheet1!N2:N1201) -> 262442.94
A6: Median | B6: =MEDIAN(Sheet1!N2:N1201) -> 823.615 | C6: =MEDIAN(Sheet1!F2:F1201) -> 364.21 | D6: =MEDIAN(Sheet1!E2:E1201) -> 3 | F6: Lower fence | G6: =G3-1.5*G5 -> -1341.4125 | I6: Laptop | J6: =SUMIF(Sheet1!D2:D1201,"Laptop",Sheet1!N2:N1201) -> 192126.56 | L6: Pending | M6: =COUNTIF(Sheet1!I2:I1201,"Pending") -> 237 | O6: Cash | P6: =SUMIF(Sheet1!H2:H1201,"Cash",Sheet1!N2:N1201) -> 259786.29
A7: Min. | B7: =MIN(Sheet1!N2:N1201) -> 11.39 | C7: =MIN(Sheet1!F2:F1201) -> 11.39 | D7: =MIN(Sheet1!E2:E1201) -> 1 | F7: Upper fence | G7: =G4+1.5*G5 -> 3330.4075 | I7: Tablet | J7: =SUMIF(Sheet1!D2:D1201,"Tablet",Sheet1!N2:N1201) -> 186568.95 | L7: Shipped | M7: =COUNTIF(Sheet1!I2:I1201,"Shipped") -> 235 | O7: Gift Card | P7: =SUMIF(Sheet1!H2:H1201,"Gift Card",Sheet1!N2:N1201) -> 246323.92
A8: Max. | B8: =MAX(Sheet1!N2:N1201) -> 3456.4 | C8: =MAX(Sheet1!F2:F1201) -> 699.93 | D8: =MAX(Sheet1!E2:E1201) -> 5 | F8: Outlier count | G8: =COUNTIF(Sheet1!N2:N1201,">"&G7) -> 8 | I8: Monitor | J8: =SUMIF(Sheet1!D2:D1201,"Monitor",Sheet1!N2:N1201) -> 175651.41 | L8: Delivered | M8: =COUNTIF(Sheet1!I2:I1201,"Delivered") -> 231 | O8: Debit Card | P8: =SUMIF(Sheet1!H2:H1201,"Debit Card",Sheet1!N2:N1201) -> 232361.18
A9: Std dev. | B9: =STDEV(Sheet1!N2:N1201) -> 819.85656 | C9: =STDEV(Sheet1!F2:F1201) -> 197.17715 | D9: =STDEV(Sheet1!E2:E1201) -> 1.4075571 | I9: Desk | J9: =SUMIF(Sheet1!D2:D1201,"Desk",Sheet1!N2:N1201) -> 167459.93
I10: Phone | J10: =SUMIF(Sheet1!D2:D1201,"Phone",Sheet1!N2:N1201) -> 151722.39
A12: Correlation Table | I12: Customers by Referral Source | L12: Coupons used
A13: Varibales | B13: Score | C13: Strength | I13: Referral Source | J13: Customer Count | L13: Coupon Code | M13: Order Count
A14: Unit Price vs Total Price | B14: =CORREL(Sheet1!F2:F1201,Sheet1!N2:N1201) -> 0.71708109 | C14: Strong Positive | I14: Instagram | J14: =COUNTIF(Sheet1!M2:M1201,"Instagram") -> 259 | L14: FREESHIP | M14: =COUNTIF(Sheet1!L2:L1201,"FREESHIP") -> 313
A15: Quantity vs Total price | B15: =CORREL(Sheet1!E2:E1201,Sheet1!N2:N1201) -> 0.61525136 | C15: Strong Positive | I15: Email | J15: =COUNTIF(Sheet1!M2:M1201,"Email") -> 250 | L15: WINTER15 | M15: =COUNTIF(Sheet1!L2:L1201,"WINTER15") -> 292
A16: Quantity vs ItemsInCart | B16: =CORREL(Sheet1!E2:E1201,Sheet1!K2:K1201) -> 0.65006123 | C16: Strong Positive | I16: Google | J16: =COUNTIF(Sheet1!M2:M1201,"Google") -> 241 | L16: SAVE10 | M16: =COUNTIF(Sheet1!L2:L1201,"SAVE10") -> 286
A17: UnitPrice vs ItemsInCart | B17: =CORREL(Sheet1!F2:F1201,Sheet1!K2:K1201) -> 0.00060215368 | C17: No Relationship | I17: Facebook | J17: =COUNTIF(Sheet1!M2:M1201,"Facebook") -> 228 | L17: No Coupon | M17: =COUNTIF(Sheet1!L2:L1201,"No coupon") -> 309
I18: Referral | J18: =COUNTIF(Sheet1!M2:M1201,"Referral") -> 222
